<annotation>
	<folder>풍경사진</folder>
	<filename>image339.jpg</filename>
	<path>/Users/yangsuyeong/Desktop/풍경사진/image339.jpg</path>
	<source>
		<database>Unknown</database>
	</source>
	<size>
		<width>509</width>
		<height>340</height>
		<depth>3</depth>
	</size>
	<segmented>0</segmented>
	<object>
		<name>sky</name>
		<pose>Unspecified</pose>
		<truncated>0</truncated>
		<difficult>0</difficult>
		<bndbox>
			<xmin>2</xmin>
			<ymin>2</ymin>
			<xmax>508</xmax>
			<ymax>160</ymax>
		</bndbox>
	</object>
	<object>
		<name>field</name>
		<pose>Unspecified</pose>
		<truncated>1</truncated>
		<difficult>0</difficult>
		<bndbox>
			<xmin>1</xmin>
			<ymin>150</ymin>
			<xmax>506</xmax>
			<ymax>335</ymax>
		</bndbox>
	</object>
</annotation>
