<annotation>
	<folder>풍경사진</folder>
	<filename>image1689.jpg</filename>
	<path>/Users/yangsuyeong/Desktop/풍경사진/image1689.jpg</path>
	<source>
		<database>Unknown</database>
	</source>
	<size>
		<width>509</width>
		<height>340</height>
		<depth>3</depth>
	</size>
	<segmented>0</segmented>
	<object>
		<name>lake</name>
		<pose>Unspecified</pose>
		<truncated>1</truncated>
		<difficult>0</difficult>
		<bndbox>
			<xmin>7</xmin>
			<ymin>7</ymin>
			<xmax>509</xmax>
			<ymax>340</ymax>
		</bndbox>
	</object>
</annotation>
